libraryname/__init__.py
libraryname/hello.py
hellopkghuman-0.0.1.dist-info/METADATA
hellopkghuman-0.0.1.dist-info/WHEEL
hellopkghuman-0.0.1.dist-info/top_level.txt
hellopkghuman-0.0.1.dist-info/RECORD
