Metadata-Version: 2.1
Name: hellopkghuman
Version: 0.0.1
Summary: Testin PyPi
Author: Human
Author-email: <human@freitagsrunde.org>
Classifier: Development Status :: 1 - Planning
Classifier: Intended Audience :: Developers
Classifier: Programming Language :: Python :: 3
Classifier: Operating System :: POSIX
Classifier: Operating System :: MacOS :: MacOS X
Classifier: Operating System :: Microsoft :: Windows
